[
    {
        "path": "404.html",
        "type": "file",
        "md5": "3377f681f539832bb96920726d1cf4a7"
    },
    {
        "path": "assets",
        "type": "directory",
        "md5": false
    },
    {
        "path": "assets/css",
        "type": "directory",
        "md5": false
    },
    {
        "path": "/assets/css/editor.css",
        "type": "file",
        "md5": "4202808df745f2ac7ab250606fa0d272"
    },
    {
        "path": "/assets/css/main.css",
        "type": "file",
        "md5": "fa238f48f9a2ab93b0c59a116e831bca"
    },
    {
        "path": "/assets/css/style.css",
        "type": "file",
        "md5": "11bee19e86e8eda2cf9a60efd975666d"
    },
    {
        "path": "assets/dynamic",
        "type": "directory",
        "md5": false
    },
    {
        "path": "assets/js",
        "type": "directory",
        "md5": false
    },
    {
        "path": "/assets/js/scripts.js",
        "type": "file",
        "md5": "e9e5c3efbaa696d1490988cf5b30e23b"
    },
    {
        "path": "/assets/js/scripts.min.js",
        "type": "file",
        "md5": "700105c316933a8202041b6415abb233"
    },
    {
        "path": "/assets/js/svg-fix.js",
        "type": "file",
        "md5": "9b7d020c55e2b4f77ab40c97f88f9ff4"
    },
    {
        "path": "/assets/js/svg-map.js",
        "type": "file",
        "md5": "ff4392540fcf4c3d3f5e03806e112816"
    },
    {
        "path": "assets/svg",
        "type": "directory",
        "md5": false
    },
    {
        "path": "/assets/svg/svg-map.svg",
        "type": "file",
        "md5": "cf04dfd5c3cc64e0be44692fe7d976a6"
    },
    {
        "path": "authors",
        "type": "directory",
        "md5": false
    },
    {
        "path": "authors/hbh",
        "type": "directory",
        "md5": false
    },
    {
        "path": "/authors/hbh/index.html",
        "type": "file",
        "md5": "2fa413aad5ad5a0a44099e4961ab8e54"
    },
    {
        "path": "feed.json",
        "type": "file",
        "md5": "f7068d686ed92c2eecf99102c109de61"
    },
    {
        "path": "feed.xml",
        "type": "file",
        "md5": "2218c745f21865365f4d381ca79cb434"
    },
    {
        "path": "fragrance-news-latest-trends-and-updates-in-the-world-of-perfumes",
        "type": "directory",
        "md5": false
    },
    {
        "path": "/fragrance-news-latest-trends-and-updates-in-the-world-of-perfumes/index.html",
        "type": "file",
        "md5": "aa78a287b93d8ed00418fb2253625b88"
    },
    {
        "path": "fragrance-news-the-complete-guide-to-perfume-trends-and-updates",
        "type": "directory",
        "md5": false
    },
    {
        "path": "/fragrance-news-the-complete-guide-to-perfume-trends-and-updates/index.html",
        "type": "file",
        "md5": "9d9d247017d97a0ada8b326c7ec3e848"
    },
    {
        "path": "index.html",
        "type": "file",
        "md5": "7a26516f60b129fcbdd5ed9c729a78f8"
    },
    {
        "path": "robots.txt",
        "type": "file",
        "md5": "2cfebd69f1bd44316b830974696998a0"
    },
    {
        "path": "shrk-rsh-mbydt-bsby-fdl-lhlwl-llqd-aal~-lhshrt",
        "type": "directory",
        "md5": false
    },
    {
        "path": "/shrk-rsh-mbydt-bsby-fdl-lhlwl-llqd-aal~-lhshrt/index.html",
        "type": "file",
        "md5": "b913339adfa1ab9554a2be668f2b219c"
    },
    {
        "path": "shrk-rsh-mbydt-bsby-lhl-lmthl-llqd-aal~-jmyaa-nwaa-lhshrt",
        "type": "directory",
        "md5": false
    },
    {
        "path": "/shrk-rsh-mbydt-bsby-lhl-lmthl-llqd-aal~-jmyaa-nwaa-lhshrt/index.html",
        "type": "file",
        "md5": "9474444240a6da8f120094e3dee68ef9"
    },
    {
        "path": "shrk-rsh-mbydt-bsby-lhl-lmthl-lltkhls-mn-lhshrt",
        "type": "directory",
        "md5": false
    },
    {
        "path": "/shrk-rsh-mbydt-bsby-lhl-lmthl-lltkhls-mn-lhshrt/index.html",
        "type": "file",
        "md5": "11ec4292340ba3aff612364cedf6d517"
    },
    {
        "path": "sitemap.xml",
        "type": "file",
        "md5": "e8a05d7d0a83dca6da6ef7736cc764e7"
    },
    {
        "path": "sitemap.xsl",
        "type": "file",
        "md5": "03c2f9a7fdcc46ff05c435907614a0b8"
    },
    {
        "path": "tags",
        "type": "directory",
        "md5": false
    },
    {
        "path": "/tags/index.html",
        "type": "file",
        "md5": "0e7453061d07a468caf622e70a65e8ac"
    }
]